biconfigs/__init__.py
biconfigs/__version__.py
biconfigs/biconfigs.py
biconfigs/exceptions.py
biconfigs/parser_cson.py
biconfigs/parser_yaml.py
biconfigs/parsers.py
biconfigs/storages.py
biconfigs-0.1.3.dist-info/DESCRIPTION.rst
biconfigs-0.1.3.dist-info/METADATA
biconfigs-0.1.3.dist-info/RECORD
biconfigs-0.1.3.dist-info/WHEEL
biconfigs-0.1.3.dist-info/metadata.json
biconfigs-0.1.3.dist-info/top_level.txt
